effect/__init__.py
effect/_base.py
effect/_continuation.py
effect/_dispatcher.py
effect/_intents.py
effect/_sync.py
effect/_test_do_py3.py
effect/_test_utils.py
effect/_utils.py
effect/do.py
effect/fold.py
effect/io.py
effect/parallel_async.py
effect/ref.py
effect/retry.py
effect/test_async.py
effect/test_base.py
effect/test_dispatcher.py
effect/test_do.py
effect/test_fold.py
effect/test_intents.py
effect/test_io.py
effect/test_parallel_performers.py
effect/test_ref.py
effect/test_retry.py
effect/test_sync.py
effect/test_testing.py
effect/test_threads.py
effect/testing.py
effect/threads.py
effect-1.1.0.dist-info/METADATA
effect-1.1.0.dist-info/WHEEL
effect-1.1.0.dist-info/top_level.txt
effect-1.1.0.dist-info/RECORD
