Metadata-Version: 2.1
Name: effect
Version: 1.1.0
Summary: pure effects for Python
Home-page: http://github.com/python-effect/effect/
Author: Christopher Armstrong
Author-email: UNKNOWN
License: MIT
Platform: UNKNOWN
Classifier: License :: OSI Approved :: MIT License
Classifier: Programming Language :: Python :: 3
Requires-Dist: attrs
